{
  "url": "https://www.ddc.co.il/elnet-mc-2-meter",
  "slug": "elnet-mc-2-meter",
  "title": "ElNet MC-2 מונה 6/2 ערוצים | ישומי בקרה - עברית",
  "description": "",
  "og_image": "",
  "content_html": "<div class=\"rich-text\"><h3>ElNet MC-2 מונה 6/2 ערוצים</h3></div>\n<div class=\"rich-text\"><p><span><span>עד 2 מערכות תלת פאזיות למדידת אנרגיה.<br/>\nעד 6 פאזות למדידת אנרגיה.<br/>\nדיוק מדידה 0.2% (0.1% בהזמנה מיוחדת).<br/>\n1600 דגימות לכל גל.<br/>\nתצוגה רציפה של נתוני המדידה.<br/>\nאיסוף נתוני אנרגיה ל 4 חודשים.<br/>\nשעון עם תעריפי תעו\"ז.<br/>\nמדידת הרמוניות עד להרמוניה מספר 64.<br/>\nתמיכה בריבוי שפות.<br/>\nערוץ תקשורת RS485.<br/>\nתמיכה בפרוטוקולי תקשורת MODBUS/BACNET.<br/>\nמסך צבעוני 320X240 באיכות גבוהה.<br/>\nתצוגת גלים גראפית.<br/>\nהתקנה פשוטה על פס DIN.<br/>\nתקשורת TCP/IP , תמיכה בדואר אלקטרוני<br/>\nאיסוף נתונים מובנה.</span></span></p></div>\n<div class=\"rich-text\"><h3>מוצרים קשורים</h3></div>\n<div class=\"rich-text\"><p> ישומי בקרה בע״מ</p></div>\n<div class=\"rich-text\"><p>יצירת קשר</p>\n<p>טלפון: +972-3-6474998​</p>\n<p>פקס: +972-3-6474598</p>\n<p><span>דואר אלקטרוני: <a href=\"mailto:cal@ddc.co.il\">cal@ddc.co.il</a></span></p></div>\n<div class=\"rich-text\"><p>שעות פתיחה</p>\n<p>ישומי בקרה בע״מ</p>\n<p>ראשון - חמישי</p>\n<p>08:00 - 17:00</p></div>\n<div class=\"rich-text\"><p>כתובת</p>\n<p>רחוב הברזל 25, תל אביב</p>\n<p>6971035</p>\n<p>ישראל</p></div>\n<div class=\"rich-text\"><p>© Copyright - ישומי בקרה בע״מ</p></div>\n<figure class=\"content-image\"><img src=\"/assets/images/screen-shot-2021-01-20-at-22-15.png\" alt=\"Screen%20Shot%202021-01-20%20at%2022.15_\" loading=\"lazy\"/></figure>\n<figure class=\"content-image\"><img src=\"/assets/images/elnet-mc-2-meter-content-5-3.png\" alt=\"ELNet-MC2-cat-1.png\" loading=\"lazy\"/></figure>",
  "rich_text": [
    "ElNet MC-2 מונה 6/2 ערוצים",
    "עד 2 מערכות תלת פאזיות למדידת אנרגיה.\nעד 6 פאזות למדידת אנרגיה.\nדיוק מדידה 0.2% (0.1% בהזמנה מיוחדת).\n1600 דגימות לכל גל.\nתצוגה רציפה של נתוני המדידה.\nאיסוף נתוני אנרגיה ל 4 חודשים.\nשעון עם תעריפי תעו\"ז.\nמדידת הרמוניות עד להרמוניה מספר 64.\nתמיכה בריבוי שפות.\nערוץ תקשורת RS485.\nתמיכה בפרוטוקולי תקשורת MODBUS/BACNET.\nמסך צבעוני 320X240 באיכות גבוהה.\nתצוגת גלים גראפית.\nהתקנה פשוטה על פס DIN.\nתקשורת TCP/IP , תמיכה בדואר אלקטרוני\nאיסוף נתונים מובנה.",
    "מוצרים קשורים",
    "ישומי בקרה בע״מ",
    "יצירת קשר\nטלפון: +972-3-6474998\n​\nפקס: +972-3-6474598\nדואר אלקטרוני:\ncal@ddc.co.il",
    "שעות פתיחה\nישומי בקרה בע״מ\nראשון - חמישי\n08:00 - 17:00",
    "כתובת\nרחוב הברזל 25, תל אביב\n6971035\nישראל",
    "© Copyright - ישומי בקרה בע״מ"
  ],
  "images": [
    {
      "src": "/assets/images/screen-shot-2021-01-20-at-22-15.png",
      "alt": "Screen%20Shot%202021-01-20%20at%2022.15_"
    },
    {
      "src": "/assets/images/home-content-2-10.png",
      "alt": ""
    },
    {
      "src": "/assets/images/home-content-3-10.png",
      "alt": ""
    },
    {
      "src": "/assets/images/home-content-4-6.png",
      "alt": ""
    },
    {
      "src": "/assets/images/elnet-mc-2-meter-content-5-3.png",
      "alt": "ELNet-MC2-cat-1.png"
    },
    {
      "src": "/assets/images/uniart-software-content-6-4.png",
      "alt": "PQ-GR-6"
    },
    {
      "src": "/assets/images/uniart-software-content-7-4.png",
      "alt": "LTE-3"
    },
    {
      "src": "/assets/images/uniart-software-content-8-4.png",
      "alt": "LT-2"
    },
    {
      "src": "/assets/images/uniart-software-content-9-4.png",
      "alt": "LT-3"
    },
    {
      "src": "/assets/images/uniart-software-content-10-4.png",
      "alt": "LT-1"
    },
    {
      "src": "/assets/images/uniart-software-content-11-4.png",
      "alt": "LT-5"
    },
    {
      "src": "/assets/images/elnet-mc-2-meter-content-12-2.png",
      "alt": "ElNet LT תעו\"ז, הרמוניות ועוד"
    },
    {
      "src": "/assets/images/pq-gr.png",
      "alt": "ElNet PQ GR הפרעות ומדידות חשמל"
    },
    {
      "src": "/assets/images/elnet-mc-2-meter-content-14-4.png",
      "alt": "ElNet LTE"
    },
    {
      "src": "/assets/images/elnet-mc-2-meter-content-15-3.png",
      "alt": "ElNet PIC מונה תעו\"ז"
    },
    {
      "src": "/assets/images/elnet-mc-2-meter-content-16-3.png",
      "alt": "ElNet MC12 מונה 12\\36 ערוצים"
    },
    {
      "src": "/assets/images/elnet-mc-2-meter-content-17-3.png",
      "alt": "ELNet MC-8 מונה 8/24 ערוצים"
    }
  ],
  "gallery": [],
  "documents": []
}
