{
  "url": "https://www.elnet-meter.com/elnet-vip-meter",
  "slug": "elnet-vip-meter",
  "title": "ElNet VIP Meter | Control Applications",
  "description": "",
  "og_image": "",
  "content_html": "<div class=\"rich-text\"><h3>ElNet VIP General electricity measurements</h3></div>\n<div class=\"rich-text\"><p><span><span>Three-phase meter.<br/>Allows display of three-phase voltages.<br/>Allows display of three-phase currents.<br/>Enables the display of three-phase suppliers.<br/>Allows three-phase power factor display.<br/>Allows peak display of voltage, current and power factor.<br/>Allows detection of lack of phase and order of phases.<br/>Measurement accuracy 0.5%.<br/>Sophisticated and illuminated LCD display.<br/>LED indication for each phase.</span></span></p>\n<p>Simple and easy panel installation.</p></div>\n<div class=\"rich-text\"><h3>Related products</h3></div>\n<div class=\"rich-text\"><p>Control Applications Ltd</p></div>\n<div class=\"rich-text\"><p>making contact</p>\n<p>Phone: +972-3-6474998​</p>\n<p>Fax: +972-3-6474598</p>\n<p><span>Email:<a href=\"mailto:cal@ddc.co.il\">cal@ddc.co.il</a></span></p></div>\n<div class=\"rich-text\"><p>opening hours</p>\n<p>Control Applications Ltd</p>\n<p>Sunday - Thursday</p>\n<p>08:00 - 17:00</p></div>\n<div class=\"rich-text\"><p>address</p>\n<p>25 Barzel Street, Tel Aviv</p>\n<p>6971035</p>\n<p>Israel</p></div>\n<div class=\"rich-text\"><p>© Copyright - Control Applications Ltd</p></div>\n<figure class=\"content-image\"><img src=\"/assets/images/screen-shot-2021-01-20-at-22-15.png\" alt=\"Screen%20Shot%202021-01-20%20at%2022.15_\" loading=\"lazy\"/></figure>\n<figure class=\"content-image\"><img src=\"/assets/images/elnet-vip-meter-content-5-5.png\" alt=\"VIP.png\" loading=\"lazy\"/></figure>",
  "rich_text": [
    "ElNet VIP General electricity measurements",
    "Three-phase meter.\nAllows display of three-phase voltages.\nAllows display of three-phase currents.\nEnables the display of three-phase suppliers.\nAllows three-phase power factor display.\nAllows peak display of voltage, current and power factor.\nAllows detection of lack of phase and order of phases.\nMeasurement accuracy 0.5%.\nSophisticated and illuminated LCD display.\nLED indication for each phase.\nSimple and easy panel installation.",
    "Related Products",
    "Control Applications Ltd",
    "making contact\nPhone: +972-3-6474998\n​\nFax: +972-3-6474598\nEmail:\ncal@ddc.co.il",
    "opening hours\nControl Applications Ltd\nSunday - Thursday\n08:00 - 17:00",
    "Address\n25 Barzel Street, Tel Aviv\n6971035\nIsrael",
    "© Copyright - Control Applications Ltd"
  ],
  "images": [
    {
      "src": "/assets/images/screen-shot-2021-01-20-at-22-15.png",
      "alt": "Screen%20Shot%202021-01-20%20at%2022.15_"
    },
    {
      "src": "/assets/images/home-content-2-10.png",
      "alt": ""
    },
    {
      "src": "/assets/images/home-content-3-10.png",
      "alt": ""
    },
    {
      "src": "/assets/images/home-content-4-6.png",
      "alt": ""
    },
    {
      "src": "/assets/images/elnet-vip-meter-content-5-5.png",
      "alt": "VIP.png"
    },
    {
      "src": "/assets/images/elnet-vip-meter-content-6-5.jpg",
      "alt": "VIP-Power"
    },
    {
      "src": "/assets/images/elnet-va-meter-content-6-5.jpg",
      "alt": "VIP-Current"
    },
    {
      "src": "/assets/images/elnet-va-meter-content-7-5.jpg",
      "alt": "VIP-6"
    },
    {
      "src": "/assets/images/elnet-vip-meter-content-9-5.jpg",
      "alt": "VIP-4"
    },
    {
      "src": "/assets/images/elnet-vip-meter-content-10-5.jpg",
      "alt": "VIP-3"
    },
    {
      "src": "/assets/images/elnet-vip-meter-content-11-5.jpg",
      "alt": "VIP-1"
    }
  ],
  "gallery": [],
  "documents": [
    {
      "label": "שרטוטים",
      "url": "https://www.elnet-meter.com/_files/ugd/9a8771_cb9e62abdacd4034b057d540c74a23ba.pdf",
      "file": "elnet-vip-meter-sketch.pdf"
    },
    {
      "label": "הורד מסמכים",
      "url": "https://www.elnet-meter.com/_files/ugd/9a8771_edaec8c729e64cc98b42f7fcb5269fac.pdf",
      "file": "elnet-vip-meter-doc.pdf"
    }
  ]
}
